{
  "file_name": "11650031.pdf",
  "sections": {
    "general": "hydroblasting technician 1 career objective an enthusiastic, team oriented and polished professional seeking employment with a company that values a proactive attitude and solid ambition. i am seeking a rewarding career allowing me to contribute to the growth of the company by increasing productivity and ensuring employer's key objectives are met. summary of skills carpentry excellent leadership skills building maintenance customer service oriented environmental coordination efficient time management adherence with all safety regulations effective problem solving",
    "experience": "company name june 2014 to current hydroblasting technician 1 city , state properly operates hoses on vacuum trucks; hydroblasting guns; and manipulate controls on robotic equipment. prepare jobsite for hydro blasting. monitor hydroblasting operations. perform job duties in a safe manner, in compliance with policies, procedures and practices. wear personnel protective equipment (ppe) as defined by state regulations. correct deficiencies that may cause accidents, injuries, lost productivity or harm to equipment or that are inconsistent with client's requirements. assist with hydroblasting and tank cleaningâ in various refineries. company name november 2012 to june 2015 construction assistant city , state performed prep work including masking, sanding and filling holes. interior and exterior painting. built and placed plywood/wall systems; installed doors and windows. constructed concrete forms, poured concrete by pump and bucket barrowed or shoveled. utilized jack hammers, compressors and power tools for daily task. company name june 2012 to current building maintenance city , state perform general building maintenance to include but not limited to theâ building grounds, landscaping as well as pressure washing. uses various hand and power tools to repair faucets, plumbing and lighting fixtures. respond quickly to emergency situations and customer concerns.",
    "education": "knowledge-first empowerment academy august 2016 high school diploma : general education",
    "certifications": "basic plus safety - july 2016 twic - april 2012 nccer - june 2010"
  }
}