{
  "file_name": "12820557.pdf",
  "sections": {
    "general": "sales associate highlights computer proficiency client relations",
    "experience": "sales associate october 2014 to current company name ï¼​ city , state responsibilities assist store management in merchandising the store in accordance with company directed standards. supervise the sales staff to generate sales through effective sales techniques and approved customer service practices. maintain current knowledge of the product and how to apply it while servicing the customer. sell the merchandise.assist the store manager and assistant manager to ensure the store is school and inventory account ready. supervise the staff in the absence of the store manager and assistant manage. assist in the training of sales staff on company policies and procedures and in particular, selling techniques. ensure staff is well versed in company directed customer service practices. comply with all company directed policies and procedures as they relate to the store operations; receiving of merchandise, store opening and closing, cash register transactions, daily cash reconciliation and inventory control. maintain security of the store and understand the operations of the store security system. skills used participated in various incentive programs and contests designed to support achievement of production goals. worked independently and as part of a team to achieve numerous objectives. described use and operation of merchandise to customers. received and processed cash and credit payments for in-store purchases. opened and closed the store, including counting cash, opening and closing cash registers and creating staff assignments. used pos systems to accurately take orders and receive payments. sales associate march 2014 to february 2015 company name ï¼​ city , state responsibilities assist store management in merchandising the store in accordance with company directed standards. supervise the sales staff to generate sales through effective sales techniques and approved customer service practices. maintain current knowledge of the product and how to apply it while servicing the customer. sell the merchandise.assist the store manager and assistant manager to ensure the store is school and inventory account ready. supervise the staff in the absence of the store manager and assistant manage. assist in the training of sales staff on company policies and procedures and in particular, selling techniques. ensure staff is well versed in company directed customer service practices. comply with all company directed policies and procedures as they relate to the store operations; receiving of merchandise, store opening and closing, cash register transactions, daily cash reconciliation and inventory control. maintain security of the store and understand the operations of the store security system. skills used participated in various incentive programs and contests designed to support achievement of production goals. worked independently and as part of a team to achieve numerous objectives. described use and operation of merchandise to customers. received and processed cash and credit payments for in-store purchases. opened and closed the store, including counting cash, opening and closing cash registers and creating staff assignments. used pos systems to accurately take orders and receive payments. team member/cashier february 2013 to december 2013 company name ï¼​ city , state responsibilities participated in various incentive programs and contests designed to support achievement of production goals. worked independently and as part of a team to achieve numerous objectives. described use and operation of merchandise to customers. received and processed cash and credit payments for in-store purchases. opened and closed the store, including counting cash, opening and closing cash registers and creating staff assignments. used pos systems to accurately take orders and receive payments skills used assist store management in merchandising the store in accordance with company directed standards. supervise the sales staff to generate sales through effective sales techniques and approved customer service practices. maintain current knowledge of the product and how to apply it while servicing the customer. sell the merchandise.assist the store manager and assistant manager to ensure the store is school and inventory account ready. supervise the staff in the absence of the store manager and assistant manage. assist in the training of sales staff on company policies and procedures and in particular, selling techniques. ensure staff is well versed in company directed customer service practices. comply with all company directed policies and procedures as they relate to the store operations; receiving of merchandise, store opening and closing, cash register transactions, daily cash reconciliation and inventory control. maintain security of the store and understand the operations of the store security system. administrative assistant/receptionist august 2011 to january 2013 company name ï¼​ city , state responsibilities drafted meeting agendas, supplied advance materials and executed follow-up for meetings and team conferences. managed the receptionist area, including greeting visitors and responding to telephone and in-person requests for information. designed electronic file systems and maintained electronic and paper files. maintained the front desk and reception area in a neat and organized fashion. received and screened a high volume of internal and external communications, including email and mail. skills used mathematical aptitude customer- and service-oriented ms office proficient pos systems exceptional customer service cash handling accuracy excel spreadsheets excellent communication skills understands grammar flexible schedule",
    "education": "ba : communications , 2018 university of phoenix ï¼​ city , state , us ba in communications - marketing and sales university of phoenix - phoenix, az 2014 to 2018 professional affiliations team member/cashier presentations team conferences",
    "skills": "and sales, marketing, sales, cash, customer service, point of sale, pos, pos systems, receptionist, retail sales, cash register, closing, credit, effective sales, generate sales, incentive programs, inventory, inventory control, merchandising, of sales, operations, payments, reconciliation, sales staff, sales techniques, sales through, security, selling techniques, the sales, training, associate, sales associate, administrative assistant, cash handling, excel, excellent communication skills, file, file systems, front desk, greeting, ms office, telephone, cashier, client relations"
  }
}