{
  "file_name": "36392131.pdf",
  "sections": {
    "general": "revenue cycle advocate",
    "summary": "dedicated and focused office manager/supervisor who excels at prioritizing, completing multiple tasks simultaneously and following through to achieve project goals. seeking a role of increased responsibility and authority.energetic revenue cycle advocate with 20+ years experience in high-level executive support roles. organized and professional. highlights microsoft office proficiency strong interpersonal skills excel spreadsheets medical terminology self-directed meeting planning results-oriented report development meticulous attention to detail report writing time management billing and coding professional and mature workers' compensation knowledge strong problem solver claims appeal procedures advanced ms office suite knowledge insurance eligibility verifications resourceful accomplishments coordinated all department functions for team of 10+ employees.received a merit raise for strong attention to detail, exemplary customer service and team-player attitude.successfully planned and executed corporate meetings, lunches and special events for groups of 10+ employees. planned and executed all aspects of a major office headquarter move.increased office organization by developing more efficient filing system and customer database protocols.promoted to revenue cycle advocate.successfully planned and executed corporate meetings, lunches and special events for groups of 10+ employees.",
    "experience": "06/2011 to current revenue cycle advocate company name ï¼​ city , state planned travel arrangements for 2 executives and 10+ staff. educate and train clinics and hospital departments on epic, signature, ms word, excel, emdeon and payment manager system. assist clinical staff and office staff their assigned work queue. monitor trends on staff and provide training & updates to company data base systems. assist with patient account merge on duplicate guarantor acct, provide assistance to patients such as medicaid, physician reach out & financial assistance. planned meetings and prepared conference rooms.wrote reports and correspondence from dictation and handwritten notes and send weekly status reports to all clinical managers on trends, audits from the clinic wq's errors from office staff and patient complaints work contested work charges received from customer service. collecting self pay payments from patients and post in the epic system set payment plans in epic financial assistance using search of america and on point system. 09/2009 to 06/2011 payment reconciliation rep company name ï¼​ city , state research unidentified payments on epic system, signature, emdeon system payment manager system, and commercial insurance websites. created pdf files on epic system create naming conventions for electronic files in epic electronic payment postings on epic system wachovia lock box denials and electronic lockbox receipts in epic resolve unidentified payments follow up with independent clinics and insurance companies for missing payment or unidentified electronic remits and paper remit. drafted meeting agendas, supplied advance materials and executed follow-up for meetings and team conferences.managed the receptionist area, including greeting visitors and responding to telephone and in-person requests for information.designed electronic file systems and maintained electronic and paper files.served as central point of contact for all outside vendors needing to gain access to the building.maintained an up-to-made copies, sent faxes and handled all incoming and outgoing correspondence. department organizational chart. 06/2007 to 09/2009 patient accounts rep iii company name ï¼​ city , state insurance follow up for denied claims and self pay after created and maintained spreadsheets using advanced excel functions and calculations to develop reports and lists.managed daily office operations and maintenance of equipment.isurance balances work atb report for insurance follow-up work dun level report for guarantor/patient follow-up work bill-hold report for guarantor follow-up appeals for medical necessity to insurance companies. 10/2002 to 06/2007 medical insurance specialist iii company name ï¼​ city , state insurance follow-up, customer service, served as central point of contact for all outside vendors needing to gain access to the building.made copies, sent faxes and handled all incoming and outgoing correspondence.organized files, developed spreadsheets, faxed reports and scanned documents. 01/2000 to 06/2002 medical billing /recovery specialist company name ï¼​ city , state billing and collections insurance follow up for denied claims and self pay after insurance balances credit balances - refunds verify demographic information verification list from ssi for billing errors set budget plans answer in/out bound calls use automated dialer system medical terminology insurance verification follow up with doctor office for accurate cpt and icd-9 codes obtained for maximum reimbursement. customer service and clerical duties. 09/1990 to 09/1997 health unit coordinator company name ï¼​ city , state duties involve standard administrative responsibilities, answering multi-line phones, making copies, scheduling appointments and maintaining supplies.cooperated with medicare, medicaid and private insurance providers to resolve billing issues.managed daily office operations and maintenance of equipment.created and maintained spreadsheets using advanced excel functions and calculations to develop reports and lists.received and distributed faxes and mail in a timely manner.properly routed agreements, contracts and invoices through the signature process.made copies, sent faxes and handled all incoming and outgoing correspondence.dispersed incoming mail to correct recipients throughout the office.maintained an up-to-date department organizational chart.drafted meeting agendas, supplied advance materials and executed follow-up for meetings and team conferences. admit patients, administer and maintain patient records, break down medical charts for record keeping and coordinate billing. communicate with the clinical staff to ensure all appropriate patient information gathered responsible for typing up discharge instructions for a patient.",
    "education": "6 1990 high school diploma : business northern high school durham nc united states ï¼​ city , state , us top 10% of class emphasis in businessoffice administration courseworkcoursework in administrative technology and coursework in human resource management and business administration 2002 business diploma : medical billing & coding georgia medical (everestuniversity) atlanta ga united states ï¼​ city , state , us top 10% of class, emphasis in medical billing and coding, medical terminology,coursework in human resource management and business administration bachelor of science : business administration management walden university ï¼​ city , state , us top 10% of class,emphasis in management and team building, coursework in administrative technology, coursework in human resource management and business administration",
    "skills": "experience with epic system, epicare, emdeon, training and educating staff on epic wq's, creating workers comp cases in epic, signature, idx, medical manager, ms word, excel, nc tracks, customer service skills, collect payment over the phone and posting payments in epic"
  }
}